threads_post/__init__.py
threads_post/threads_post.py
ThreadsPost-0.0.1.dist-info/LICENSE
ThreadsPost-0.0.1.dist-info/METADATA
ThreadsPost-0.0.1.dist-info/WHEEL
ThreadsPost-0.0.1.dist-info/top_level.txt
ThreadsPost-0.0.1.dist-info/RECORD
