Metadata-Version: 2.1
Name: ThreadsPost
Version: 0.0.1
Summary: This is Python library to just post to Threads
Home-page: https://github.com/Mr-SuperInsane/ThreadsPost
Author: Nao Matsukami
Author-email: info@mr-insane.net
Classifier: Development Status :: 4 - Beta
Classifier: Intended Audience :: Developers
Classifier: Topic :: Software Development :: Build Tools
Classifier: License :: OSI Approved :: MIT License
Classifier: Programming Language :: Python :: 3
Classifier: Programming Language :: Python :: 3.7
Classifier: Programming Language :: Python :: 3.8
Classifier: Programming Language :: Python :: 3.9
License-File: LICENSE
Requires-Dist: pytz ==2021.3
